MatTool/MatTool.py
MatTool/__init__.py
MatTool-1.0.1.dist-info/LICENSE
MatTool-1.0.1.dist-info/METADATA
MatTool-1.0.1.dist-info/WHEEL
MatTool-1.0.1.dist-info/top_level.txt
MatTool-1.0.1.dist-info/RECORD
