Metadata-Version: 2.1
Name: MatTool
Version: 1.0.1
Summary: A python package to perform Matrix Operations
Home-page: https://github.com/SACHIN1625/MatTool/
Author: Sachin_S
Author-email: sachinshanmugam07@gmail.com
License: UNKNOWN
Platform: UNKNOWN
Classifier: Programming Language :: Python :: 3
Classifier: License :: OSI Approved :: MIT License
Classifier: Operating System :: OS Independent
Requires-Python: >=3.5
